{
"items": [
 {
   "code": "romdia",
   "type": "Console Repair",
   "price": "$18.11 "
 },
 {
   "code": "loqir1",
   "type": "Video Rental",
   "price": "$5.84 "
 },
 {
   "code": "1wb5rf",
   "type": "Steam",
   "price": "$90.30 "
 },
 {
   "code": "ly5z6p",
   "type": "Bayonetta 2",
   "price": "$98.36 "
 },
 {
   "code": "9dwtvf",
   "type": "Xbox Live",
   "price": "$17.57 "
 },
 {
   "code": "7aqno9",
   "type": "Wii Sports",
   "price": "$2.28 "
 },
 {
   "code": "w139oc",
   "type": "Nintendo Switch Online",
   "price": "$41.97 "
 },
 {
   "code": "8l2xfo",
   "type": "Super Smash Bros. Ultimate",
   "price": "$68.25 "
 },
 {
   "code": "ankdua",
   "type": "Playstation Plus",
   "price": "$81.48 "
 },
 {
   "code": "5m2813",
   "type": "Metroid Prime Trilogy",
   "price": "$59.34 "
 }
]
}